myavm/02_generate_samples.py
myavm/03_train_embedding.py
myavm/04_plot_training_history.py
myavm/05_generate_embedding_samples.py
myavm/06_train_classifier.py
myavm/__init__.py
myavm/audio.py
myavm/audio_model.py
myavm/buffer.pickle
myavm/final_baseline_expermental_.ipynb
myavm/gsheets.py
myavm/image.py
myavm/l3embedding.log
myavm/log.py
myavm/model.py
myavm/pre_trained_supervised.py
myavm/seeds_test.pickle
myavm/supervised.py
myavm/test.py
myavm/testing.py
myavm/train.py
myavm/training_utils.py
myavm/vgg_pretrained.py
myavm/vision_model.py
myavm/data/__init__.py
myavm/data/log.py
myavm/data/ontology.py
myavm/data/utils.py
myavm/data/avc/__init__.py
myavm/data/avc/sample.py
myavm/data/avc/subsets.py
myavm/data/usc/Arabic_Music.py
myavm/data/usc/DCASE.py
myavm/data/usc/RAVDESS.py
myavm/data/usc/__init__.py
myavm/data/usc/dcase2013.py
myavm/data/usc/esc50.py
myavm/data/usc/features.py
myavm/data/usc/folds.py
myavm/data/usc/us8k.py
myavm/data/usc/vggish/README.md
myavm/data/usc/vggish/__init__.py
myavm/data/usc/vggish/mel_features.py
myavm/data/usc/vggish/vggish_input.py
myavm/data/usc/vggish/vggish_params.py
myavm/data/usc/vggish/vggish_postprocess.py
myavm/data/usc/vggish/vggish_slim.py
myavm/data/usc/vggish/vggish_smoke_test.py
myavm-0.0.2.dist-info/WHEEL
myavm-0.0.2.dist-info/METADATA
myavm-0.0.2.dist-info/RECORD
